libmultilabel/__init__.py
libmultilabel/common_utils.py
libmultilabel/logging.py
libmultilabel/linear/__init__.py
libmultilabel/linear/data_utils.py
libmultilabel/linear/linear.py
libmultilabel/linear/metrics.py
libmultilabel/linear/preprocessor.py
libmultilabel/linear/tree.py
libmultilabel/linear/utils.py
libmultilabel/nn/__init__.py
libmultilabel/nn/attentionxml.py
libmultilabel/nn/data_utils.py
libmultilabel/nn/metrics.py
libmultilabel/nn/model.py
libmultilabel/nn/nn_utils.py
libmultilabel/nn/networks/__init__.py
libmultilabel/nn/networks/bert.py
libmultilabel/nn/networks/bert_attention.py
libmultilabel/nn/networks/caml.py
libmultilabel/nn/networks/kim_cnn.py
libmultilabel/nn/networks/labelwise_attention_networks.py
libmultilabel/nn/networks/modules.py
libmultilabel/nn/networks/xml_cnn.py
libmultilabel-0.8.1.dist-info/licenses/LICENSE
libmultilabel-0.8.1.dist-info/METADATA
libmultilabel-0.8.1.dist-info/WHEEL
libmultilabel-0.8.1.dist-info/top_level.txt
libmultilabel-0.8.1.dist-info/RECORD
